.coveragerc
.gitignore
.travis.yml
MANIFEST.in
README.rst
base.cfg
bootstrap.py
buildout.cfg
doc.txt
setup.py
travis.cfg
collective/__init__.py
collective.portlet.contact.egg-info/PKG-INFO
collective.portlet.contact.egg-info/SOURCES.txt
collective.portlet.contact.egg-info/dependency_links.txt
collective.portlet.contact.egg-info/entry_points.txt
collective.portlet.contact.egg-info/namespace_packages.txt
collective.portlet.contact.egg-info/not-zip-safe
collective.portlet.contact.egg-info/requires.txt
collective.portlet.contact.egg-info/top_level.txt
collective/portlet/__init__.py
collective/portlet/test.html
collective/portlet/contact/TODO.txt
collective/portlet/contact/__init__.py
collective/portlet/contact/addressbook.py
collective/portlet/contact/configure.zcml
collective/portlet/contact/i18n.py
collective/portlet/contact/rebuild_i18n.sh
collective/portlet/contact/testing.py
collective/portlet/contact/upgrades.py
collective/portlet/contact/upgrades.zcml
collective/portlet/contact/utils.py
collective/portlet/contact/browser/__init__.py
collective/portlet/contact/browser/configure.zcml
collective/portlet/contact/browser/contact_view.pt
collective/portlet/contact/browser/contact_view.py
collective/portlet/contact/browser/controlpanel.pt
collective/portlet/contact/browser/controlpanel.py
collective/portlet/contact/browser/jpegPhoto.py
collective/portlet/contact/browser/searcher.py
collective/portlet/contact/browser/static/README.txt
collective/portlet/contact/browser/static/contact.gif
collective/portlet/contact/browser/static/defaultUser.png
collective/portlet/contact/browser/static/jquery.autocomplete.css
collective/portlet/contact/browser/static/jquery.autocomplete.js
collective/portlet/contact/browser/static/jquery.bgiframe.min.js
collective/portlet/contact/dummy/__init__.py
collective/portlet/contact/dummy/addressbook.py
collective/portlet/contact/dummy/configure.zcml
collective/portlet/contact/dummy/controlpanel.pt
collective/portlet/contact/dummy/controlpanel.py
collective/portlet/contact/ldap/__init__.py
collective/portlet/contact/ldap/addressbook.py
collective/portlet/contact/ldap/configure.zcml
collective/portlet/contact/ldap/controlpanel.pt
collective/portlet/contact/ldap/controlpanel.py
collective/portlet/contact/ldap/jpegPhoto.py
collective/portlet/contact/ldap/utils.py
collective/portlet/contact/locales/collective.portlet.contact.pot
