Metadata-Version: 1.0
Name: collective.portlet.contact
Version: 1.1.2
Summary: Display LDAP contacts in Plone portlets.
Home-page: http://www.makina-corpus.com
Author: Sylvain Boureliou
Author-email: sylvain.boureliou@makina-corpus.com
License: GPL
Keywords: plone portlet ldap contact
Platform: UNKNOWN
Classifier: Environment :: Web Environment
Classifier: License :: OSI Approved :: GNU General Public License (GPL)
Classifier: Operating System :: OS Independent
Classifier: Framework :: Zope2
Classifier: Framework :: Plone
Classifier: Framework :: Plone :: 4.0
Classifier: Framework :: Plone :: 4.1
Classifier: Framework :: Plone :: 4.2
Classifier: Framework :: Plone :: 4.3
Classifier: Programming Language :: Python
Classifier: Programming Language :: Python :: 2.6
Classifier: Programming Language :: Python :: 2.7
